quantgov/__init__.py
quantgov/__main__.py
quantgov/corpus.py
quantgov/nlp.py
quantgov/utils.py
quantgov/ml/__init__.py
quantgov/ml/candidate_sets.py
quantgov/ml/estimation.py
quantgov/ml/evaluation.py
quantgov/ml/structures.py
quantgov/ml/training.py
quantgov/ml/utils.py
quantgov-0.6.4.dist-info/AUTHORS.rst
quantgov-0.6.4.dist-info/LICENSE
quantgov-0.6.4.dist-info/METADATA
quantgov-0.6.4.dist-info/WHEEL
quantgov-0.6.4.dist-info/entry_points.txt
quantgov-0.6.4.dist-info/top_level.txt
quantgov-0.6.4.dist-info/RECORD
