Metadata-Version: 2.1
Name: quantgov
Version: 0.6.4
Summary: A Policy Analytics Framework
Home-page: https://github.com/QuantGov/quantgov
Author: QuantGov
Author-email: info@quantgov.org
License: MIT
Keywords: quantgov economics policy government machine learning
Classifier: Development Status :: 3 - Alpha
Classifier: Intended Audience :: Science/Research
Classifier: Topic :: Scientific/Engineering :: Information Analysis
Classifier: License :: OSI Approved :: MIT License
Classifier: Programming Language :: Python :: 3
Classifier: Programming Language :: Python :: 3.6
Classifier: Programming Language :: Python :: 3.7
Classifier: Programming Language :: Python :: 3.8
License-File: LICENSE
License-File: AUTHORS.rst
Requires-Dist: decorator
Requires-Dist: joblib
Requires-Dist: pandas
Requires-Dist: requests
Requires-Dist: scikit-learn
Requires-Dist: scipy
Requires-Dist: textstat
Provides-Extra: nlp
Requires-Dist: textblob ; extra == 'nlp'
Requires-Dist: nltk ; extra == 'nlp'
Provides-Extra: s3driver
Requires-Dist: sqlalchemy ; extra == 's3driver'
Requires-Dist: boto3 ; extra == 's3driver'
Provides-Extra: testing
Requires-Dist: pytest-flake8 ; extra == 'testing'
